mustafalib/__init__.py
mustafalib-0.0.1.dist-info/LICENSE
mustafalib-0.0.1.dist-info/METADATA
mustafalib-0.0.1.dist-info/WHEEL
mustafalib-0.0.1.dist-info/top_level.txt
mustafalib-0.0.1.dist-info/RECORD
