Metadata-Version: 2.1
Name: mustafalib
Version: 0.0.1
Summary: A Python library for specific TikTok operations.
Home-page: https://github.com/Mustafa
Author: Mustafa
Author-email: wert1245grad@gmail.com
License: MIT
Platform: UNKNOWN
Classifier: Programming Language :: Python :: 3
Classifier: License :: OSI Approved :: MIT License
Classifier: Operating System :: OS Independent
Requires-Python: >=3.6
License-File: LICENSE
Requires-Dist: SignerPy
Requires-Dist: requests
Requires-Dist: user-agent
